simple_cdd_yaml/__init__.py
simple_cdd_yaml/actions.py
simple_cdd_yaml/recipe_interpreter.py
simple_cdd_yaml/simple_cdd_yaml.py
simple_cdd_yaml/yaml_tools.py
simple_cdd_yaml-0.1.2.dist-info/licenses/LICENSE
simple_cdd_yaml-0.1.2.dist-info/METADATA
simple_cdd_yaml-0.1.2.dist-info/WHEEL
simple_cdd_yaml-0.1.2.dist-info/entry_points.txt
simple_cdd_yaml-0.1.2.dist-info/top_level.txt
simple_cdd_yaml-0.1.2.dist-info/RECORD
