Metadata-Version: 2.4
Name: simple-cdd-yaml
Version: 0.1.2
Summary: YAML recipe interpreter for Simple-CDD
Author-email: Sietze van Buuren <s.van.buuren@gmail.com>
License: Copyright 2024 Sietze van Buuren <s.van.buuren@gmail.com>
Project-URL: Homepage, https://github.com/swvanbuuren/simple-cdd-yaml
Classifier: Programming Language :: Python :: 3
Classifier: Programming Language :: Python :: 3.8
Classifier: Programming Language :: Python :: 3.9
Classifier: Programming Language :: Python :: 3.10
Classifier: Programming Language :: Python :: 3.11
Classifier: License :: OSI Approved :: MIT License
Classifier: Operating System :: OS Independent
Requires-Python: >=3.8
License-File: LICENSE
Requires-Dist: pyyaml>=6.0.2
Requires-Dist: jinja2>=3.1.4
Dynamic: license-file
